baker/__init__.py
baker/cli.py
baker/commands.py
baker/logger.py
baker/recipe.py
baker/repository.py
baker/secret.py
baker/settings.py
baker/storage.py
baker/template.py
bakercm-0.4.5.dist-info/licenses/LICENSE
bakercm-0.4.5.dist-info/METADATA
bakercm-0.4.5.dist-info/WHEEL
bakercm-0.4.5.dist-info/entry_points.txt
bakercm-0.4.5.dist-info/top_level.txt
bakercm-0.4.5.dist-info/RECORD
